pyanist/chord_generator.py
pyanist/chord_matcher.py
pyanist/cli.py
pyanist/dictionaries/english-us.json
pyanist/test_chord_generator.py
pyanist/test_match_words_with_chords.py
pyanist/word-frequency-lists/word-freq-top5000.csv
pyanist-0.1.3.dist-info/entry_points.txt
pyanist-0.1.3.dist-info/LICENSE
pyanist-0.1.3.dist-info/WHEEL
pyanist-0.1.3.dist-info/METADATA
pyanist-0.1.3.dist-info/RECORD
